wizata_dsapi/__init__.py
wizata_dsapi/api_config.py
wizata_dsapi/api_dto.py
wizata_dsapi/api_interface.py
wizata_dsapi/bucket.py
wizata_dsapi/business_label.py
wizata_dsapi/context.py
wizata_dsapi/dataframe_toolkit.py
wizata_dsapi/datapoint.py
wizata_dsapi/datastore.py
wizata_dsapi/ds_dataframe.py
wizata_dsapi/dsapi_json_encoder.py
wizata_dsapi/evaluation.py
wizata_dsapi/execution.py
wizata_dsapi/experiment.py
wizata_dsapi/group_system.py
wizata_dsapi/ilogger.py
wizata_dsapi/insight.py
wizata_dsapi/mlmodel.py
wizata_dsapi/model_toolkit.py
wizata_dsapi/paged_query_result.py
wizata_dsapi/pipeline.py
wizata_dsapi/pipeline_deployment.py
wizata_dsapi/pipeline_image.py
wizata_dsapi/plot.py
wizata_dsapi/request.py
wizata_dsapi/script.py
wizata_dsapi/solution_component.py
wizata_dsapi/streamlit_utils.py
wizata_dsapi/template.py
wizata_dsapi/trigger.py
wizata_dsapi/twin.py
wizata_dsapi/twinregistration.py
wizata_dsapi/version.py
wizata_dsapi/wizard_function.py
wizata_dsapi/wizard_request.py
wizata_dsapi/wizata_dsapi_client.py
wizata_dsapi/words.py
wizata_dsapi/models/__init__.py
wizata_dsapi/models/common.py
wizata_dsapi/plots/__init__.py
wizata_dsapi/plots/common.py
wizata_dsapi/scripts/__init__.py
wizata_dsapi/scripts/common.py
wizata_dsapi-1.3.52.dist-info/licenses/LICENSE.txt
wizata_dsapi-1.3.52.dist-info/METADATA
wizata_dsapi-1.3.52.dist-info/WHEEL
wizata_dsapi-1.3.52.dist-info/top_level.txt
wizata_dsapi-1.3.52.dist-info/RECORD
