Metadata-Version: 2.4
Name: wizata_dsapi
Version: 1.3.52
Summary: Wizata Data Science Toolkit
Author: Wizata S.A.
Author-email: info@wizata.com
License-File: LICENSE.txt
Requires-Dist: pandas==1.5.3; python_version < "3.11"
Requires-Dist: pandas==2.2.3; python_version >= "3.11" and python_version < "3.12"
Requires-Dist: pandas>=2.3.3; python_version >= "3.12"
Requires-Dist: numpy==1.26.4; python_version < "3.12"
Requires-Dist: numpy>=2.3.3; python_version >= "3.12"
Requires-Dist: dill==0.3.6; python_version < "3.12"
Requires-Dist: dill==0.4.0; python_version >= "3.12"
Requires-Dist: protobuf==3.20.3; python_version < "3.12"
Requires-Dist: protobuf>=5.29.5; python_version >= "3.12"
Requires-Dist: msal==1.30.0; python_version < "3.12"
Requires-Dist: msal>=1.34.0; python_version >= "3.12"
Requires-Dist: joblib==1.5.2; python_version < "3.12"
Requires-Dist: joblib>=1.2.0; python_version >= "3.12"
Requires-Dist: requests==2.28.2; python_version < "3.11"
Requires-Dist: requests>=2.32.5; python_version >= "3.11"
Requires-Dist: setuptools==67.6.0; python_version < "3.11"
Requires-Dist: setuptools>=80.9.0; python_version >= "3.11"
Requires-Dist: plotly==5.13.1; python_version < "3.12"
Requires-Dist: plotly>=6.3.1; python_version >= "3.12"
Provides-Extra: all
Requires-Dist: pandas==1.5.3; python_version < "3.11" and extra == "all"
Requires-Dist: pandas==2.2.3; (python_version >= "3.11" and python_version < "3.12") and extra == "all"
Requires-Dist: pandas>=2.3.3; python_version >= "3.12" and extra == "all"
Requires-Dist: numpy==1.26.4; python_version < "3.12" and extra == "all"
Requires-Dist: numpy>=2.3.3; python_version >= "3.12" and extra == "all"
Requires-Dist: dill==0.3.6; python_version < "3.12" and extra == "all"
Requires-Dist: dill==0.4.0; python_version >= "3.12" and extra == "all"
Requires-Dist: protobuf==3.20.3; python_version < "3.12" and extra == "all"
Requires-Dist: protobuf>=5.29.5; python_version >= "3.12" and extra == "all"
Requires-Dist: msal==1.30.0; python_version < "3.12" and extra == "all"
Requires-Dist: msal>=1.34.0; python_version >= "3.12" and extra == "all"
Requires-Dist: joblib==1.5.2; python_version < "3.12" and extra == "all"
Requires-Dist: joblib>=1.2.0; python_version >= "3.12" and extra == "all"
Requires-Dist: requests==2.28.2; python_version < "3.11" and extra == "all"
Requires-Dist: requests>=2.32.5; python_version >= "3.11" and extra == "all"
Requires-Dist: setuptools==67.6.0; python_version < "3.11" and extra == "all"
Requires-Dist: setuptools>=80.9.0; python_version >= "3.11" and extra == "all"
Requires-Dist: plotly==5.13.1; python_version < "3.12" and extra == "all"
Requires-Dist: plotly>=6.3.1; python_version >= "3.12" and extra == "all"
Requires-Dist: matplotlib==3.7.1; python_version < "3.11" and extra == "all"
Requires-Dist: matplotlib>=3.10.6; python_version >= "3.11" and extra == "all"
Requires-Dist: scikit-learn==1.2.2; python_version < "3.12" and extra == "all"
Requires-Dist: scikit-learn>=1.7.2; python_version >= "3.12" and extra == "all"
Requires-Dist: adtk==0.6.2; extra == "all"
Requires-Dist: scipy==1.10.1; python_version < "3.12" and extra == "all"
Requires-Dist: scipy>=1.16.2; python_version >= "3.12" and extra == "all"
Requires-Dist: xgboost==1.7.4; python_version < "3.12" and extra == "all"
Requires-Dist: xgboost>=3.0.5; python_version >= "3.12" and extra == "all"
Requires-Dist: u8darts==0.25.0; python_version < "3.12" and extra == "all"
Requires-Dist: u8darts>=0.38.0; python_version >= "3.12" and extra == "all"
Requires-Dist: optuna==3.3.0; python_version < "3.12" and extra == "all"
Requires-Dist: optuna>=4.5.0; python_version >= "3.12" and extra == "all"
Requires-Dist: explainerdashboard==0.4.2.1; python_version < "3.12" and extra == "all"
Requires-Dist: ipywidgets==8.0.4; python_version < "3.12" and extra == "all"
Requires-Dist: ipywidgets>=8.1.7; python_version >= "3.12" and extra == "all"
Requires-Dist: kaleido==0.2.1; python_version < "3.12" and extra == "all"
Requires-Dist: kaleido>=1.1.0; python_version >= "3.12" and extra == "all"
Requires-Dist: pytest==7.2.2; python_version < "3.12" and extra == "all"
Requires-Dist: pytest>=8.4.2; python_version >= "3.12" and extra == "all"
Requires-Dist: pytest-cov==4.0.0; python_version < "3.12" and extra == "all"
Requires-Dist: pytest-cov>=7.0.0; python_version >= "3.12" and extra == "all"
Requires-Dist: shapely==2.0.1; python_version < "3.12" and extra == "all"
Requires-Dist: shapely>=2.1.2; python_version >= "3.12" and extra == "all"
Requires-Dist: pyodbc==4.0.35; python_version < "3.12" and extra == "all"
Requires-Dist: pyodbc>=5.2.0; python_version >= "3.12" and extra == "all"
Requires-Dist: torch==2.7.1; (python_version >= "3.11" and python_version < "3.12") and extra == "all"
Requires-Dist: torch>=2.8.0; python_version >= "3.12" and extra == "all"
Dynamic: author
Dynamic: author-email
Dynamic: license-file
Dynamic: provides-extra
Dynamic: requires-dist
Dynamic: summary
